clustering_optimum/__init__.py
clustering_optimum/score_function.py
clustering_optimum/.ipynb_checkpoints/score_function-checkpoint.py
clustering_optimum-1.0.0.dist-info/METADATA
clustering_optimum-1.0.0.dist-info/WHEEL
clustering_optimum-1.0.0.dist-info/licenses/LICENSE
clustering_optimum-1.0.0.dist-info/RECORD
