Metadata-Version: 2.4
Name: clustering_optimum
Version: 1.0.0
Summary: Finding the optimum resolution parameter for clustering scRNA-seq data analyzed with _scanpy_, by calculating the BIC score or the Calinski-Harabasz score of each clustering.
Project-URL: Homepage, https://gitbio.ens-lyon.fr/spatial-cell-id/clustering_optimum
Author-email: Marco Uderzo <marco.uderzo@ens-lyon.fr>, Sergio Sarnataro <sergio.sarnataro@ens-lyon.fr>
License: GPL-3.0-or-later
License-File: LICENSE
Classifier: Operating System :: OS Independent
Classifier: Programming Language :: Python :: 3
Requires-Python: >=3.9
